markcli/__init__.py
markcli/markcli.py
markcli-0.1.4.dist-info/LICENSE
markcli-0.1.4.dist-info/METADATA
markcli-0.1.4.dist-info/WHEEL
markcli-0.1.4.dist-info/entry_points.txt
markcli-0.1.4.dist-info/top_level.txt
markcli-0.1.4.dist-info/RECORD
